asahi/__init__.py
asahi/__version__.py
asahi/py.typed
asahi-0.2.0.dist-info/LICENSE
asahi-0.2.0.dist-info/WHEEL
asahi-0.2.0.dist-info/METADATA
asahi-0.2.0.dist-info/RECORD
