Metadata-Version: 2.1
Name: asahi
Version: 0.2.0
Summary: A small package to provide utility functions to libraries that has optional installs / extras
Home-page: https://github.com/kalaspuff/asahi
License: MIT
Keywords: asahi,extras,optional installs,extras requires,extra packages,optional packages,lazy import
Author: Carl Oscar Aaro
Author-email: hello@carloscar.com
Requires-Python: >=3.7,<4.0
Classifier: Development Status :: 1 - Planning
Classifier: Intended Audience :: Developers
Classifier: License :: OSI Approved :: MIT License
Classifier: Programming Language :: Python
Classifier: Programming Language :: Python :: 3
Classifier: Programming Language :: Python :: 3.10
Classifier: Programming Language :: Python :: 3.7
Classifier: Programming Language :: Python :: 3.8
Classifier: Programming Language :: Python :: 3.9
Classifier: Topic :: Software Development
Classifier: Topic :: Software Development :: Libraries
Classifier: Typing :: Typed
Provides-Extra: extras
Requires-Dist: asahi-extras (>=0.1.0); extra == "extras"
Project-URL: Repository, https://github.com/kalaspuff/asahi
